weehok/weehok.py
weehok-1.0.dist-info/LICENSE
weehok-1.0.dist-info/METADATA
weehok-1.0.dist-info/WHEEL
weehok-1.0.dist-info/top_level.txt
weehok-1.0.dist-info/RECORD
