Metadata-Version: 2.1
Name: weehok
Version: 1.0
Summary: It just makes ur life easy so why not use it?
Home-page: https://pageup.lt/
Author: 0xleft
License: Apache License 2.0
License-File: LICENSE
